ckanext/__init__.py
ckanext/likes/__init__.py
ckanext/likes/cli.py
ckanext/likes/config.py
ckanext/likes/config_declaration.yaml
ckanext/likes/helpers.py
ckanext/likes/plugin.py
ckanext/likes/views.py
ckanext/likes/logic/__init__.py
ckanext/likes/logic/action.py
ckanext/likes/logic/auth.py
ckanext/likes/logic/schema.py
ckanext/likes/migration/likes/alembic.ini
ckanext/likes/migration/likes/env.py
ckanext/likes/migration/likes/script.py.mako
ckanext/likes/migration/likes/versions/d54e61a33b84_add_likes_table.py
ckanext/likes/model/__init__.py
ckanext/likes/model/base.py
ckanext/likes/model/like.py
ckanext/likes/templates/likes/snippets/widget.html
ckanext/likes/tests/__init__.py
ckanext/likes/tests/conftest.py
ckanext/likes/tests/test_plugin.py
ckanext/likes/tests/test_views.py
ckanext/likes/tests/benchmarks/__init__.py
ckanext/likes/tests/benchmarks/test_speed.py
ckanext/likes/tests/e2e/__init__.py
ckanext/likes/tests/e2e/conftest.py
ckanext/likes/tests/e2e/test_home.py
ckanext/likes/tests/logic/test_action.py
ckanext/likes/tests/logic/test_auth.py
ckanext/likes/tests/logic/test_schema.py
ckanext/likes/tests/model/__init__.py
ckanext/likes/tests/model/test_like.py
ckanext_likes-0.0.1.dist-info/METADATA
ckanext_likes-0.0.1.dist-info/WHEEL
ckanext_likes-0.0.1.dist-info/entry_points.txt
ckanext_likes-0.0.1.dist-info/top_level.txt
ckanext_likes-0.0.1.dist-info/RECORD
